flaskoidc_dcr
